hass_websocket_client/__init__.py
hass_websocket_client/client.py
hass_websocket_client/exceptions.py
hass_websocket_client/models.py
hass_websocket_client-0.2.0.dist-info/LICENSE
hass_websocket_client-0.2.0.dist-info/METADATA
hass_websocket_client-0.2.0.dist-info/WHEEL
hass_websocket_client-0.2.0.dist-info/RECORD
