Metadata-Version: 2.1
Name: hass-websocket-client
Version: 0.2.0
Summary: HomeAssistant WS wrapper library
License: MIT
Author: iTecAI
Author-email: matteovh@gmail.com
Requires-Python: >=3.12,<4.0
Classifier: License :: OSI Approved :: MIT License
Classifier: Programming Language :: Python :: 3
Classifier: Programming Language :: Python :: 3.12
Requires-Dist: pydantic (>=2.5.3,<3.0.0)
Requires-Dist: websockets (>=12.0,<13.0)
